expiration.py
expiration-1.0.dist-info/DESCRIPTION.rst
expiration-1.0.dist-info/METADATA
expiration-1.0.dist-info/RECORD
expiration-1.0.dist-info/WHEEL
expiration-1.0.dist-info/metadata.json
expiration-1.0.dist-info/top_level.txt
