Metadata-Version: 2.0
Name: expiration
Version: 1.0
Summary: Manages complex expiration rules.
Home-page: https://bitbucket.org/ericvsmith/expiration
Author: Eric V. Smith
Author-email: eric@trueblade.com
License: Apache License Version 2.0
Platform: UNKNOWN
Classifier: Development Status :: 4 - Beta
Classifier: Intended Audience :: Developers
Classifier: License :: OSI Approved :: Apache Software License
Classifier: Topic :: Software Development :: Libraries :: Python Modules
Classifier: Programming Language :: Python :: 2.7
Classifier: Programming Language :: Python :: 3.4
Classifier: Programming Language :: Python :: 3.5
